honkaistarrail/calculator.py
honkaistarrail/modal.py
honkaistarrail/src/data/gacha/gacha_data.py
honkaistarrail/starrail.py
honkaistarrail-0.0.8.dist-info/WHEEL
honkaistarrail-0.0.8.dist-info/METADATA
honkaistarrail-0.0.8.dist-info/RECORD
