Metadata-Version: 2.1
Name: honkaistarrail
Version: 0.0.8
Summary: Asynchronous module for working with API Honkai: Star Rail
Home-page: https://github.com/DEViantUA/HonkaiStarRail.py
Author: None
Requires-Python: >=3.7,<4.0
Classifier: Programming Language :: Python :: 3
Classifier: Programming Language :: Python :: 3.7
Classifier: Programming Language :: Python :: 3.8
Classifier: Programming Language :: Python :: 3.9
Classifier: Programming Language :: Python :: 3.10
Classifier: Programming Language :: Python :: 3.11
Project-URL: Repository, https://github.com/DEViantUA/HonkaiStarRail.py
